mbg/mbg/__init__.py
mbg-0.1.0.dist-info/LICENSE
mbg-0.1.0.dist-info/METADATA
mbg-0.1.0.dist-info/WHEEL
mbg-0.1.0.dist-info/top_level.txt
mbg-0.1.0.dist-info/RECORD
