Metadata-Version: 2.2
Name: mbg
Version: 0.1.0
Summary: Meise Botanic Garden Python packages namespace
License: MIT
Project-URL: homepage, https://www.plantentuinmeise.be
Project-URL: repository, https://github.com/AgentschapPlantentuinMeise/mbg
Project-URL: documentation, https://github.com/AgentschapPlantentuinMeise/mbg/docs
Requires-Python: >=3.6
License-File: LICENSE
Provides-Extra: dev
Requires-Dist: pytest; extra == "dev"
Requires-Dist: flake8; extra == "dev"
